yadt/__init__.py
yadt/const.py
yadt/converter.py
yadt/high_level.py
yadt/main.py
yadt/pdfinterp.py
yadt/progress_monitor.py
yadt/translation_config.py
yadt/asynchronize/__init__.py
yadt/document_il/__init__.py
yadt/document_il/il_version_1.py
yadt/document_il/il_version_1.rnc
yadt/document_il/il_version_1.rng
yadt/document_il/il_version_1.xsd
yadt/document_il/xml_converter.py
yadt/document_il/backend/__init__.py
yadt/document_il/backend/pdf_creater.py
yadt/document_il/frontend/__init__.py
yadt/document_il/frontend/il_creater.py
yadt/document_il/midend/__init__.py
yadt/document_il/midend/il_translator.py
yadt/document_il/midend/layout_parser.py
yadt/document_il/midend/paragraph_finder.py
yadt/document_il/midend/styles_and_formulas.py
yadt/document_il/midend/typesetting.py
yadt/document_il/translator/__init__.py
yadt/document_il/translator/cache.py
yadt/document_il/translator/translator.py
yadt/document_il/utils/fontmap.py
yadt/document_il/utils/layout_helper.py
yadt/docvision/README.md
yadt/docvision/__init__.py
yadt/docvision/doclayout.py
yadt/docvision/rpc_doclayout.py
yadt-0.1.5.dist-info/METADATA
yadt-0.1.5.dist-info/WHEEL
yadt-0.1.5.dist-info/entry_points.txt
yadt-0.1.5.dist-info/licenses/LICENSE
yadt-0.1.5.dist-info/RECORD
