Metadata-Version: 2.4
Name: yadt
Version: 0.1.5
Summary: Yet Another Document Translator
Project-URL: Homepage, https://github.com/funstory-ai/yadt
Project-URL: Issues, https://github.com/funstory-ai/yadt/issues
License-Expression: AGPL-3.0
License-File: LICENSE
Keywords: PDF
Classifier: Operating System :: OS Independent
Classifier: Programming Language :: Python :: 3
Requires-Python: <3.13,>=3.10
Requires-Dist: bitstring>=4.3.0
Requires-Dist: configargparse>=1.7
Requires-Dist: httpx>=0.27.0
Requires-Dist: huggingface-hub>=0.27.0
Requires-Dist: msgpack>=1.1.0
Requires-Dist: numpy>=2.0.2
Requires-Dist: onnx>=1.17.0
Requires-Dist: onnxruntime>=1.16.1
Requires-Dist: openai>=1.59.3
Requires-Dist: opencv-python>=4.10.0.84
Requires-Dist: orjson>=3.10.14
Requires-Dist: pdfminer-six>=20240706
Requires-Dist: peewee>=3.17.8
Requires-Dist: pymupdf>=1.25.1
Requires-Dist: rich>=13.9.4
Requires-Dist: toml>=0.10.2
Requires-Dist: tqdm>=4.67.1
Requires-Dist: xsdata[cli,lxml,soap]>=24.12
